teamcity_extra/__init__.py
teamcity_extra/messages.py
teamcity_messages_extra-1.1.0.dist-info/LICENSE
teamcity_messages_extra-1.1.0.dist-info/METADATA
teamcity_messages_extra-1.1.0.dist-info/WHEEL
teamcity_messages_extra-1.1.0.dist-info/top_level.txt
teamcity_messages_extra-1.1.0.dist-info/RECORD
